textsorter/__init__.py
textsorter/textsorter.py
textsorter-1.0.1.dist-info/LICENSE
textsorter-1.0.1.dist-info/METADATA
textsorter-1.0.1.dist-info/WHEEL
textsorter-1.0.1.dist-info/top_level.txt
textsorter-1.0.1.dist-info/RECORD
