Metadata-Version: 2.1
Name: textsorter
Version: 1.0.1
Summary: This simple script sorts all the words in the text by popularity in descending order 
Home-page: UNKNOWN
Author: UNKNOWN
Author-email: UNKNOWN
License: UNKNOWN
Keywords: textsorter
Platform: UNKNOWN
